bayesian_network_generator/__init__.py
bayesian_network_generator/cli.py
bayesian_network_generator/core.py
bayesian_network_generator/network_generator.py
bayesian_network_generator/quality_metrics.py
bayesian_network_generator-1.0.1.dist-info/LICENSE
bayesian_network_generator-1.0.1.dist-info/METADATA
bayesian_network_generator-1.0.1.dist-info/WHEEL
bayesian_network_generator-1.0.1.dist-info/entry_points.txt
bayesian_network_generator-1.0.1.dist-info/top_level.txt
bayesian_network_generator-1.0.1.dist-info/RECORD
