Metadata-Version: 2.1
Name: bayesian-network-generator
Version: 1.0.1
Summary: Advanced Bayesian Network Generator with comprehensive topology and distribution support
Home-page: https://github.com/rudzanimulaudzi/bayesian-network-generator
Author: Rudzani Mulaudzi
Author-email: rudzani.mulaudzi2@students.wits.ac.za
Project-URL: Bug Reports, https://github.com/rudzanimulaudzi/bayesian-network-generator/issues
Project-URL: Source, https://github.com/rudzanimulaudzi/bayesian-network-generator
Project-URL: Documentation, https://github.com/rudzanimulaudzi/bayesian-network-generator/blob/main/README.md
Keywords: bayesian networks machine learning probabilistic graphical models
Classifier: Development Status :: 5 - Production/Stable
Classifier: Intended Audience :: Science/Research
Classifier: Intended Audience :: Education
Classifier: Topic :: Scientific/Engineering :: Artificial Intelligence
Classifier: Topic :: Scientific/Engineering :: Information Analysis
Classifier: License :: OSI Approved :: MIT License
Classifier: Programming Language :: Python :: 3
Classifier: Programming Language :: Python :: 3.8
Classifier: Programming Language :: Python :: 3.9
Classifier: Programming Language :: Python :: 3.10
Classifier: Programming Language :: Python :: 3.11
Classifier: Programming Language :: Python :: 3.12
Requires-Python: >=3.8
License-File: LICENSE
Requires-Dist: numpy >=1.9.0
Requires-Dist: pandas >=1.0.0
Requires-Dist: networkx >=2.0.0
Requires-Dist: pgmpy >=0.1.17
Requires-Dist: matplotlib >=3.0.0
Requires-Dist: seaborn >=0.9.0
Requires-Dist: scikit-learn >=0.20.0
Requires-Dist: scipy >=1.0.0
Provides-Extra: dev
Requires-Dist: pytest >=6.0 ; extra == 'dev'
Requires-Dist: pytest-cov >=2.0 ; extra == 'dev'
Requires-Dist: black >=21.0 ; extra == 'dev'
Requires-Dist: flake8 >=3.8 ; extra == 'dev'
